konfetti/__init__.py
konfetti/_async.py
konfetti/_compat.py
konfetti/cache.py
konfetti/core.py
konfetti/environ.py
konfetti/exceptions.py
konfetti/laziness.py
konfetti/loaders.py
konfetti/log.py
konfetti/mixins.py
konfetti/pytest_plugin.py
konfetti/utils.py
konfetti/contrib/__init__.py
konfetti/contrib/django.py
konfetti/contrib/flask.py
konfetti/vault/__init__.py
konfetti/vault/asynchronous.py
konfetti/vault/base.py
konfetti/vault/core.py
konfetti/vault/synchronous.py
konfetti-0.8.0.dist-info/LICENSE
konfetti-0.8.0.dist-info/METADATA
konfetti-0.8.0.dist-info/WHEEL
konfetti-0.8.0.dist-info/top_level.txt
konfetti-0.8.0.dist-info/RECORD
