Metadata-Version: 2.1
Name: konfetti
Version: 0.8.0
Summary: `konfetti` provides a framework-independent way for configuration of applications or libraries written in Python.
Home-page: https://github.com/kiwicom/konfetti
Author: Dmitry Dygalo
Author-email: dmitry.dygalo@kiwi.com
License: MIT
Platform: UNKNOWN
Classifier: Development Status :: 4 - Beta
Classifier: Intended Audience :: Developers
Classifier: Environment :: Console
Classifier: Operating System :: OS Independent
Classifier: Programming Language :: Python
Classifier: Programming Language :: Python :: 2
Classifier: Programming Language :: Python :: 2.7
Classifier: Programming Language :: Python :: 3
Classifier: Programming Language :: Python :: 3.5
Classifier: Programming Language :: Python :: 3.6
Classifier: Programming Language :: Python :: 3.7
Classifier: Programming Language :: Python :: Implementation :: CPython
Classifier: License :: OSI Approved :: MIT License
Requires-Python: >=2.7, !=3.0.*, !=3.1.*, !=3.2.*, !=3.3.*, !=3.4.*
Requires-Dist: attrs
Requires-Dist: python-dotenv
Provides-Extra: async-vault
Requires-Dist: aiohttp ; extra == 'async-vault'
Requires-Dist: tenacity ; extra == 'async-vault'
Provides-Extra: vault
Requires-Dist: hvac ; extra == 'vault'
Requires-Dist: tenacity ; extra == 'vault'
